Workbook
Name Anos: APP!$D$14
Name investir: APP!$D$13
Name rend_mens: APP!$D$15
Name Rendimento_carteira: APP!$D$9

Sheet APP
C7: CONFIGURAÇÕES
C8: Salário | D8: 2000
C9: Rendimento na carteira | D9: 0.01
C10: Sugestão de investimento | D10: =D8*30% -> 600
C12: INVESTIMENTO MENSAL
C13: Quanto investir por mês? | D13: 200
C14: Quantos anos? | D14: 5
C15: Taxa de rendimento mensal? | D15: 0.0108
C16: Patrimonio acumulado? | D16: =FV(rend_mens,Anos*12,investir*-1) -> 16760.804
C17: Dividendos mensais? | D17: =D16*Rendimento_carteira -> 167.60804
C20: CENÁRIOS | E20: Dividendo
B21: 2 | C21: Quanto em 2 anos? | D21: =FV($D$15,$B21*12,$D$13*-1) -> 5446.1727 | E21: =D21*Rendimento_carteira -> 54.461727
B22: 5 | C22: Quanto em 5 anos? | D22: =FV($D$15,$B22*12,$D$13*-1) -> 16760.804 | E22: =D22*Rendimento_carteira -> 167.60804
B23: 10 | C23: Quanto em 10 anos? | D23: =FV($D$15,$B23*12,$D$13*-1) -> 48691.533 | E23: =D23*Rendimento_carteira -> 486.91533
B24: 20 | C24: Quanto em 20 anos? | D24: =FV($D$15,$B24*12,$D$13*-1) -> 225409.8 | E24: =D24*Rendimento_carteira -> 2254.098
C29: TIPO | D29: Agressivo
C30: VALOR A SER INVESTIDO POR MÊS | D30: =investir -> 200
C32: TIPO DE FII | D32: PERCENTUAL SUGERIDO | E32: VALOR
C33: PAPEL | D33: =VLOOKUP($D$29&"-"&C33,APOIO!A2:D20,4,FALSE) -> 0.5 | E33: =$D$30*D33 -> 100
C34: TIJOLO | D34: =VLOOKUP($D$29&"-"&C34,APOIO!A3:D21,4,FALSE) -> 0.1 | E34: =$D$30*D34 -> 20
C35: HÍBRIDOS | D35: =VLOOKUP($D$29&"-"&C35,APOIO!A4:D22,4,FALSE) -> 0.05 | E35: =$D$30*D35 -> 10
C36: FOFs | D36: =VLOOKUP($D$29&"-"&C36,APOIO!A5:D23,4,FALSE) -> 0.05 | E36: =$D$30*D36 -> 10
C37: DESENVOLVIMENTO | D37: =VLOOKUP($D$29&"-"&C37,APOIO!A6:D24,4,FALSE) -> 0.2 | E37: =$D$30*D37 -> 40
C38: HOTELARIAS | D38: =VLOOKUP($D$29&"-"&C38,APOIO!A7:D25,4,FALSE) -> 0.1 | E38: =$D$30*D38 -> 20
E39: =SUM(E33:E38) -> 200

Sheet APOIO
A2: CHAVE | B2: PERFIL | C2: TIPO DE FII | D2: %
A3: Conservador-PAPEL | B3: Conservador | C3: PAPEL | D3: 0.3 | G3: Conservador-PAPEL | H3: =APP!D33=VLOOKUP(G3,$A$2:$D$20,4,FALSE) -> FALSE
A4: Conservador-TIJOLO | B4: Conservador | C4: TIJOLO | D4: 0.5
A5: Conservador-HÍBRIDOS | B5: Conservador | C5: HÍBRIDOS | D5: 0.1
A6: Conservador-FOFs | B6: Conservador | C6: FOFs | D6: 0.1
A7: Conservador-DESENVOLVIMENTO | B7: Conservador | C7: DESENVOLVIMENTO | D7: 0
A8: Conservador-HOTELARIAS | B8: Conservador | C8: HOTELARIAS | D8: 0
A9: Moderado-PAPEL | B9: Moderado | C9: PAPEL | D9: 0.32
A10: Moderado-TIJOLO | B10: Moderado | C10: TIJOLO | D10: 0.35
A11: Moderado-HÍBRIDOS | B11: Moderado | C11: HÍBRIDOS | D11: 0.08
A12: Moderado-FOFs | B12: Moderado | C12: FOFs | D12: 0.05
A13: Moderado-DESENVOLVIMENTO | B13: Moderado | C13: DESENVOLVIMENTO | D13: 0.1
A14: Moderado-HOTELARIAS | B14: Moderado | C14: HOTELARIAS | D14: 0.1
A15: Agressivo-PAPEL | B15: Agressivo | C15: PAPEL | D15: 0.5
... A20: Agressivo-HOTELARIAS | B20: Agressivo | C20: HOTELARIAS | D20: 0.1
